{
    "key": "group_5b9ad27c6ca80",
    "title": "Courts Landing",
    "fields": [
        {
            "key": "field_5b9ad2c65b3f1",
            "label": "Intro Panel",
            "name": "",
            "aria-label": "",
            "type": "tab",
            "instructions": "",
            "required": 0,
            "conditional_logic": 0,
            "wrapper": {
                "width": "",
                "class": "",
                "id": ""
            },
            "placement": "left",
            "endpoint": 0,
            "selected": 0
        },
        {
            "key": "field_5b9ad2e25b3f2",
            "label": "Instructions",
            "name": "",
            "aria-label": "",
            "type": "message",
            "instructions": "",
            "required": 0,
            "conditional_logic": 0,
            "wrapper": {
                "width": "",
                "class": "",
                "id": ""
            },
            "message": "Court Intro panel",
            "new_lines": "wpautop",
            "esc_html": 0
        },
        {
            "key": "field_5b9ad31edd73f",
            "label": "Content",
            "name": "courts_intro_content",
            "aria-label": "",
            "type": "wysiwyg",
            "instructions": "",
            "required": 0,
            "conditional_logic": 0,
            "wrapper": {
                "width": "",
                "class": "",
                "id": ""
            },
            "default_value": "",
            "tabs": "text",
            "media_upload": 1,
            "toolbar": "full",
            "delay": 0
        },
        {
            "key": "field_5b9ad40a545c5",
            "label": "Map Panel",
            "name": "",
            "aria-label": "",
            "type": "tab",
            "instructions": "",
            "required": 0,
            "conditional_logic": 0,
            "wrapper": {
                "width": "",
                "class": "",
                "id": ""
            },
            "placement": "left",
            "endpoint": 0,
            "selected": 0
        },
        {
            "key": "field_5b9ad41e545c6",
            "label": "Instructions",
            "name": "",
            "aria-label": "",
            "type": "message",
            "instructions": "",
            "required": 0,
            "conditional_logic": 0,
            "wrapper": {
                "width": "",
                "class": "",
                "id": ""
            },
            "message": "Interactive map panel",
            "new_lines": "wpautop",
            "esc_html": 0
        },
        {
            "key": "field_5b9ad45c545c7",
            "label": "Content",
            "name": "courts_map_content",
            "aria-label": "",
            "type": "wysiwyg",
            "instructions": "",
            "required": 0,
            "conditional_logic": 0,
            "wrapper": {
                "width": "",
                "class": "",
                "id": ""
            },
            "default_value": "",
            "tabs": "text",
            "media_upload": 1,
            "toolbar": "full",
            "delay": 0
        },
        {
            "key": "field_5b9ad498e4fd1",
            "label": "Sentencing Panel",
            "name": "",
            "aria-label": "",
            "type": "tab",
            "instructions": "",
            "required": 0,
            "conditional_logic": 0,
            "wrapper": {
                "width": "",
                "class": "",
                "id": ""
            },
            "placement": "left",
            "endpoint": 0,
            "selected": 0
        },
        {
            "key": "field_5b9ad4aae4fd2",
            "label": "Instructions",
            "name": "",
            "aria-label": "",
            "type": "message",
            "instructions": "",
            "required": 0,
            "conditional_logic": 0,
            "wrapper": {
                "width": "",
                "class": "",
                "id": ""
            },
            "message": "Sentencing and data tables panel",
            "new_lines": "wpautop",
            "esc_html": 0
        },
        {
            "key": "field_5b9ad4bbe4fd3",
            "label": "Content",
            "name": "courts_sentencing_content",
            "aria-label": "",
            "type": "wysiwyg",
            "instructions": "",
            "required": 0,
            "conditional_logic": 0,
            "wrapper": {
                "width": "",
                "class": "",
                "id": ""
            },
            "default_value": "",
            "tabs": "text",
            "media_upload": 1,
            "toolbar": "full",
            "delay": 0
        }
    ],
    "location": [
        [
            {
                "param": "post_template",
                "operator": "==",
                "value": "courts-landing.php"
            }
        ]
    ],
    "menu_order": 0,
    "position": "acf_after_title",
    "style": "default",
    "label_placement": "top",
    "instruction_placement": "label",
    "hide_on_screen": [
        "the_content"
    ],
    "active": true,
    "description": "",
    "show_in_rest": false,
    "display_title": "",
    "modified": 1779909228
}
